aggenerico/AG.py
Aggenerico-0.0.3.dist-info/METADATA
Aggenerico-0.0.3.dist-info/WHEEL
Aggenerico-0.0.3.dist-info/top_level.txt
Aggenerico-0.0.3.dist-info/RECORD
