Metadata-Version: 2.1
Name: Aggenerico
Version: 0.0.3
Summary: Exemplo de pacote PyPI
Home-page: https://github.com/marcyhel/AGgenerico
Author: Marcyhel da Silva Menezes
Author-email: h.marcyhel2012@gmail.com
License: MIT License
Keywords: Pacote
Platform: UNKNOWN
